{
  "team1": {
    "coach": "Brycewright2",
    "roster": [
      {
        "pokemon": "Incineroar",
        "startform": "Incineroar",
        "nickname": "Incineroar",
        "kills": 0,
        "deaths": 1,
        "causeofdeath": null,
        "support": 0,
        "damagedone": 82,
        "hphealed": -22,
        "luck": -0.2,
        "remaininghealth": 0,
        "lines": [],
        "confusion": null,
        "psn": null,
        "brn": null,
        "par": null,
        "frz": null,
        "tox": "zaps mcgee",
        "Curse": null
      },
      {
        "pokemon": "Zygarde-10%",
        "startform": "Zygarde",
        "nickname": "Zygarde",
        "kills": 1,
        "deaths": 1,
        "causeofdeath": null,
        "support": 0,
        "damagedone": 152,
        "hphealed": 0,
        "luck": 0.0,
        "remaininghealth": 0,
        "lines": [],
        "confusion": null,
        "psn": null,
        "brn": null,
        "par": null,
        "frz": null,
        "tox": "zaps mcgee",
        "Curse": null
      },
      {
        "pokemon": "Tornadus-Therian",
        "startform": "Tornadus",
        "nickname": "Tornadus",
        "kills": 1,
        "deaths": 0,
        "causeofdeath": null,
        "support": 1,
        "damagedone": 196,
        "hphealed": 90,
        "luck": -1.32,
        "remaininghealth": 88,
        "lines": [],
        "confusion": null,
        "psn": null,
        "brn": null,
        "par": null,
        "frz": null,
        "tox": "garth brooks",
        "Curse": null
      },
      {
        "pokemon": "Hippowdon",
        "startform": "Hippowdon",
        "nickname": "Hippowdon",
        "kills": 0,
        "deaths": 0,
        "causeofdeath": null,
        "support": 2,
        "damagedone": 48,
        "hphealed": -12,
        "luck": 0.68,
        "remaininghealth": 45,
        "lines": [],
        "confusion": null,
        "psn": null,
        "brn": null,
        "par": null,
        "frz": null,
        "tox": null,
        "Curse": null
      },
      {
        "pokemon": "Mew",
        "startform": "Mew",
        "nickname": "Mew",
        "kills": 1,
        "deaths": 1,
        "causeofdeath": null,
        "support": 1,
        "damagedone": 166,
        "hphealed": 0,
        "luck": 0.36,
        "remaininghealth": 0,
        "lines": [],
        "confusion": null,
        "psn": null,
        "brn": null,
        "par": null,
        "frz": null,
        "tox": "garth brooks",
        "Curse": null
      },
      {
        "pokemon": "Empoleon",
        "startform": "Empoleon",
        "nickname": "Empoleon",
        "kills": 1,
        "deaths": 1,
        "causeofdeath": null,
        "support": 0,
        "damagedone": 188,
        "hphealed": 0,
        "luck": 1.34,
        "remaininghealth": 0,
        "lines": [],
        "confusion": null,
        "psn": null,
        "brn": null,
        "par": null,
        "frz": null,
        "tox": null,
        "Curse": null
      }
    ],
    "wins": 1,
    "forfeit": 0,
    "score": 2,
    "megaevolved": false,
    "usedzmove": false,
    "timesswitched": 13,
    "selfdeaths": 0,
    "remaininghealth": 133,
    "totalhealth": 600,
    "kills": 4,
    "deaths": 4,
    "luck": 0.86,
    "damagedone": 832,
    "hphealed": 56,
    "support": 4,
    "activemon": "Tornadus",
    "Toxic Spikes": null,
    "Spikes": null,
    "Stealth Rock": null,
    "Future Sight": null,
    "Doom Desire": null,
    "Sandstorm": null,
    "Hail": null,
    "Leech Seed": null
  },
  "team2": {
    "coach": "ShatteredSimisear",
    "roster": [
      {
        "pokemon": "Stonjourner",
        "startform": "Stonjourner",
        "nickname": "believe",
        "kills": 1,
        "deaths": 1,
        "causeofdeath": null,
        "support": 0,
        "damagedone": 48,
        "hphealed": 0,
        "luck": 0.26,
        "remaininghealth": 0,
        "lines": [],
        "confusion": null,
        "psn": null,
        "brn": null,
        "par": null,
        "frz": null,
        "tox": null,
        "Curse": null
      },
      {
        "pokemon": "Dragapult",
        "startform": "Dragapult",
        "nickname": "s p o o k",
        "kills": 2,
        "deaths": 1,
        "causeofdeath": null,
        "support": 0,
        "damagedone": 182,
        "hphealed": -18,
        "luck": 0.16,
        "remaininghealth": 0,
        "lines": [],
        "confusion": null,
        "psn": null,
        "brn": null,
        "par": null,
        "frz": null,
        "tox": null,
        "Curse": null
      },
      {
        "pokemon": "Zapdos",
        "startform": "Zapdos",
        "nickname": "zaps mcgee",
        "kills": 1,
        "deaths": 1,
        "causeofdeath": null,
        "support": 3,
        "damagedone": 44,
        "hphealed": 66,
        "luck": -1.46,
        "remaininghealth": 0,
        "lines": [],
        "confusion": null,
        "psn": null,
        "brn": "Mew",
        "par": null,
        "frz": null,
        "tox": null,
        "Curse": null
      },
      {
        "pokemon": "Whimsicott",
        "startform": "Whimsicott",
        "nickname": "o",
        "kills": 0,
        "deaths": 1,
        "causeofdeath": null,
        "support": 0,
        "damagedone": 46,
        "hphealed": 0,
        "luck": -0.24,
        "remaininghealth": 0,
        "lines": [],
        "confusion": null,
        "psn": null,
        "brn": null,
        "par": null,
        "frz": null,
        "tox": null,
        "Curse": null
      },
      {
        "pokemon": "Gligar",
        "startform": "Gligar",
        "nickname": "garth brooks",
        "kills": 0,
        "deaths": 1,
        "causeofdeath": null,
        "support": 4,
        "damagedone": 166,
        "hphealed": 190,
        "luck": 1.52,
        "remaininghealth": 0,
        "lines": [],
        "confusion": null,
        "psn": null,
        "brn": null,
        "par": null,
        "frz": null,
        "tox": null,
        "Curse": null
      },
      {
        "pokemon": "Klang",
        "startform": "Klang",
        "nickname": "u in for it now",
        "kills": 0,
        "deaths": 1,
        "causeofdeath": null,
        "support": 0,
        "damagedone": 37,
        "hphealed": -6,
        "luck": -1.1,
        "remaininghealth": 0,
        "lines": [],
        "confusion": null,
        "psn": null,
        "brn": null,
        "par": null,
        "frz": null,
        "tox": null,
        "Curse": null
      }
    ],
    "wins": 0,
    "forfeit": 1,
    "score": 0,
    "megaevolved": false,
    "usedzmove": false,
    "timesswitched": 11,
    "selfdeaths": 2,
    "remaininghealth": 0,
    "totalhealth": 600,
    "kills": 4,
    "deaths": 6,
    "luck": -0.86,
    "damagedone": 523,
    "hphealed": 232,
    "support": 7,
    "activemon": "garth brooks",
    "Toxic Spikes": null,
    "Spikes": null,
    "Stealth Rock": "Hippowdon",
    "Future Sight": null,
    "Doom Desire": null,
    "Sandstorm": null,
    "Hail": null,
    "Leech Seed": null
  },
  "Perish Song": null,
  "numberofturns": 34,
  "turns": [],
  "replay": "https://replay.pokemonshowdown.com/gen8nationaldexag-1045208825",
  "significantevents": [
    [
      1,
      "Zapdos provided support by using Toxic"
    ],
    [
      3,
      "Zapdos killed Incineroar via tox"
    ],
    [
      4,
      "Gligar provided support by using Toxic"
    ],
    [
      4,
      "Mew provided support by using Trick Room"
    ],
    [
      5,
      "LUCK: Zapdos was burned by Mew with Scald"
    ],
    [
      7,
      "Zapdos provided support by using Toxic"
    ],
    [
      7,
      "LUCK: Zapdos missed Toxic against Mew"
    ],
    [
      9,
      "Zapdos provided support by using Toxic"
    ],
    [
      10,
      "Zygarde-10% killed Zapdos with Max Wyrmwind"
    ],
    [
      13,
      "LUCK: Empoleon landed a crit on Klang with Hydro Pump"
    ],
    [
      14,
      "Empoleon killed Whimsicott with Ice Beam"
    ],
    [
      15,
      "Stonjourner killed Empoleon with Earthquake"
    ],
    [
      16,
      "Mew killed Stonjourner with Scald"
    ],
    [
      17,
      "LUCK: Dragapult landed a crit on Mew with Shadow Ball"
    ],
    [
      17,
      "Dragapult killed Mew with Shadow Ball"
    ],
    [
      18,
      "Dragapult killed Zygarde-10% with Max Wyrmwind"
    ],
    [
      20,
      "Hippowdon provided support by using Stealth Rock"
    ],
    [
      21,
      "Gligar provided support by using Toxic"
    ],
    [
      24,
      "LUCK: Tornadus-Therian missed Hurricane against Gligar"
    ],
    [
      26,
      "Gligar provided support by using Defog"
    ],
    [
      28,
      "Hippowdon provided support by using Stealth Rock"
    ],
    [
      30,
      "Dragapult fainted via item: Life Orb"
    ],
    [
      31,
      "Klang fainted via steelbeam"
    ],
    [
      32,
      "Gligar provided support by using Toxic"
    ],
    [
      33,
      "Tornadus-Therian provided support by using Taunt"
    ]
  ],
  "errormessage": []
}